servicenow_mcp/__init__.py
servicenow_mcp/client.py
servicenow_mcp/config.py
servicenow_mcp/exceptions.py
servicenow_mcp/server.py
servicenow_mcp/tools.py
servicenow_mcp_server-0.1.1.dist-info/METADATA
servicenow_mcp_server-0.1.1.dist-info/WHEEL
servicenow_mcp_server-0.1.1.dist-info/entry_points.txt
servicenow_mcp_server-0.1.1.dist-info/licenses/LICENSE
servicenow_mcp_server-0.1.1.dist-info/RECORD
